softshell/__init__.py
softshell/exceptions.py
softshell/softshell.py
softshell-0.1.data/scripts/softshell
softshell-0.1.dist-info/LICENSE
softshell-0.1.dist-info/METADATA
softshell-0.1.dist-info/WHEEL
softshell-0.1.dist-info/top_level.txt
softshell-0.1.dist-info/RECORD
