Metadata-Version: 2.1
Name: softshell
Version: 0.1
Summary: Turn hard-coded variables into dynamic ones without refactoring.
Home-page: http://github.com/seansaito/softshell
Author: Sean Saito
Author-email: saitosean@ymail.com
License: MIT
Platform: UNKNOWN
Classifier: Development Status :: 3 - Alpha
Classifier: Programming Language :: Python :: 3.6
Requires-Dist: PyYAML (>=5.1)
